searcHPV/__init__.py
searcHPV/alignment.py
searcHPV/assemble.py
searcHPV/general.py
searcHPV/generate_alignment.py
searcHPV/generate_assemble.py
searcHPV/generate_call_fusion.py
searcHPV/generate_call_fusion_virus.py
searcHPV/genome_fusion.py
searcHPV/hpv_fusion.py
searcHPV/main.py
searcHPV/selection_contig_call_virus_insertion.py
searcHPV/virus_fusion.py
searcHPV-1.1.0.dist-info/LICENSE
searcHPV-1.1.0.dist-info/METADATA
searcHPV-1.1.0.dist-info/WHEEL
searcHPV-1.1.0.dist-info/entry_points.txt
searcHPV-1.1.0.dist-info/top_level.txt
searcHPV-1.1.0.dist-info/RECORD
