Metadata-Version: 2.1
Name: searcHPV
Version: 1.1.0
Summary: An HPV integration sites detection tool for targeted capture sequencing data
Home-page: https://github.com/WenjinGudaisy/SearcHPV
Author: Wenjin Gu
Author-email: wenjingu@umich.edu
Keywords: HPV,integration,targeted capture sequencing
Classifier: Development Status :: 3 - Alpha
Classifier: License :: OSI Approved :: MIT License
Classifier: Operating System :: Unix
Classifier: Programming Language :: Python :: 3
Classifier: Programming Language :: Python :: 3.5
Classifier: Programming Language :: Python :: 3.6
Classifier: Programming Language :: Python :: 3.7
Classifier: Programming Language :: Python :: 3.8
Classifier: Programming Language :: Python :: 3 :: Only
Requires-Python: >=3.5, <4
License-File: LICENSE
Requires-Dist: pysam
Requires-Dist: pandas
Requires-Dist: argparse
